{
  "standardAnalysis": {
    "contentRequirement": "理解平面直角坐标系的有关概念，能画出平面直角坐标系；在给定的平面直角坐标系中，能根据坐标描出点的位置，由点的位置写出坐标。",
    "academicRequirement": "能在平面直角坐标系中，根据坐标描出点的位置，由点的位置写出坐标，体会数形结合思想。",
    "teachingHint": "应引导学生经历用坐标表示点的位置的过程，体会数形结合思想，发展几何直观和空间观念。",
    "coreCompetencyNames": [
      "几何直观",
      "数形结合思想",
      "抽象能力"
    ]
  },
  "textbookAnalysis": {
    "verticalAnalysis": "本课是人教版七年级下册第七章《平面直角坐标系》的第一课时，在小学阶段学生已学过用数对表示位置（如教室座位），在此基础上引入平面直角坐标系，为后续学习坐标与图形位置、坐标与图形运动、函数及其图象等知识奠定基础。本课是初中阶段数形结合思想的起点，连接了代数与几何。",
    "crossAnalysis": "人教版教材从具体情境（如电影院座位）引入有序数对，再自然过渡到平面直角坐标系的概念，强调从实际到抽象的思维过程。相比北师大版直接给出坐标系定义，人教版更注重情境化和生活化，降低入门难度。本版本特色在于通过“数轴”类比引出坐标轴，利用网格纸辅助描点，突出直观性。",
    "bigConcept": "用有序数对表示点的位置，建立数与形的对应关系。",
    "keyKnowledge": [
      "有序数对的概念",
      "平面直角坐标系的组成（x轴、y轴、原点、象限）",
      "点的坐标表示与描点方法"
    ],
    "difficulties": [
      "教学重点：平面直角坐标系的概念及点的坐标表示",
      "教学难点：理解坐标与点的对应关系，特别是象限内点的坐标符号特征"
    ]
  },
  "learnerAnalysis": {
    "priorKnowledge": "学生已掌握数轴的概念及数轴上的点与实数的对应关系，能用有序数对（如行、列）表示位置，具备基本的正负数知识。",
    "priorExperience": "学生在生活中使用过地图上的经纬度、电影院座位号、棋盘坐标等，有“用一对数确定位置”的感性经验。",
    "cognitiveDifficulty": "学生可能难以理解为什么需要两条数轴而不是一条；坐标（a,b）的顺序易混淆；对四个象限内点的坐标符号规律缺乏自觉认识。",
    "preAssessment": "通过课堂提问或小测：给出教室座位图，让学生用（列，行）表示自己的位置；再给出数轴，请学生读出点对应的数。"
  },
  "learningObjectives": [
    {
      "content": "通过观察电影院座位图等实例，学生能说出有序数对的含义，并能用有序数对表示点的位置。",
      "category": "knowledge",
      "competencyLink": "几何直观",
      "assessmentMethod": "课堂提问"
    },
    {
      "content": "在教师引导下，学生能画出平面直角坐标系，并能根据点的坐标描出点，或由点的位置写出坐标。",
      "category": "skill",
      "competencyLink": "数形结合思想",
      "assessmentMethod": "课堂练习与后测"
    },
    {
      "content": "通过小组合作探究，学生能归纳出象限内点的坐标符号特征，并体会数学与生活的联系。",
      "category": "attitude",
      "competencyLink": "抽象能力",
      "assessmentMethod": "观察与交流表现"
    }
  ],
  "assessmentTasks": {
    "preMethod": "课堂前测（纸笔或口头）",
    "preQuestions": [
      "用数对（列，行）表示你在教室中的位置。",
      "在数轴上，点A对应的数是2，点B对应的数是-3，请标出它们的位置。"
    ],
    "prePurpose": "检测学生对有序数对和数轴的掌握情况，诊断学习起点。",
    "postMethod": "课堂后测（纸笔练习）",
    "postTasks": [
      "在给定的平面直角坐标系中，描出点A(3,2)、B(-2,1)、C(0,-3)、D(-4,-1)。",
      "写出图中点E、F、G、H的坐标。"
    ],
    "postRubric": "优秀：全部正确且能解释坐标含义；合格：描点或写坐标有少量错误（≤2个）；需辅导：错误超过2个或概念不清。"
  },
  "activities": [
    {
      "phase": "B",
      "title": "情境导入：电影院找座位",
      "duration": 3,
      "teacherAction": "展示电影院座位图，提问：如何准确找到自己的座位？引出有序数对。",
      "studentAction": "回答：需要知道几排几座。讨论如何用一对数表示位置。",
      "designIntent": "从生活情境出发，激发兴趣，引出有序数对的概念。",
      "assessmentEmbedded": "观察学生能否用“列、行”描述位置。"
    },
    {
      "phase": "O",
      "title": "明确学习目标",
      "duration": 2,
      "teacherAction": "板书课题并出示本课学习目标，解释学习路径。",
      "studentAction": "阅读目标，明确本节课要学什么、做到什么。",
      "designIntent": "让学生清楚学习方向，增强目标意识。",
      "assessmentEmbedded": ""
    },
    {
      "phase": "P-participatory",
      "title": "探索平面直角坐标系",
      "duration": 15,
      "teacherAction": "先让学生尝试：如何用一对数表示平面上任意一点？提供网格纸，不直接讲解，让学生先困惑。然后引导：类比数轴，能否用两条互相垂直的数轴？展示坐标系，讲解x轴、y轴、原点、象限。",
      "studentAction": "先独立尝试在网格纸上标记点，发现困难；然后小组交流，讨论如何用两个数表示；最后听教师讲解，完善认知。",
      "designIntent": "困难前置：先让学生经历“无法用单一数轴表示点”的困惑，再引出坐标系，加深理解。过程保留：学生保留尝试的痕迹。",
      "assessmentEmbedded": "巡视观察学生的尝试过程，记录典型错误，用于后续讲解。"
    },
    {
      "phase": "P-post",
      "title": "巩固练习：描点与写坐标",
      "duration": 8,
      "teacherAction": "出示练习题，指导学生独立完成，并请学生板演。",
      "studentAction": "独立完成描点与写坐标练习，核对答案，纠正错误。",
      "designIntent": "检测学生是否掌握坐标表示与描点技能，及时反馈。",
      "assessmentEmbedded": "后测练习，教师巡视并个别辅导。"
    },
    {
      "phase": "S",
      "title": "课堂总结与拓展",
      "duration": 5,
      "teacherAction": "引导学生回顾本课核心概念，提问：平面直角坐标系有什么作用？与数轴有何关系？",
      "studentAction": "总结有序数对、坐标轴、象限等概念，举例说明坐标在生活中的应用。",
      "designIntent": "归纳提升，建立知识结构，为下一课（坐标与图形位置）铺垫。",
      "assessmentEmbedded": "通过提问了解学生整体掌握情况。"
    }
  ],
  "homework": {
    "requiredTitle1": "基础练习：描点与写坐标",
    "requiredDesc1": "教材第68页练习第1、2题：在坐标系中描出给定点，并写出各点的坐标。",
    "requiredTitle2": "应用练习：描述位置",
    "requiredDesc2": "用平面直角坐标系描述你书桌上某本书或文具的位置（以书桌左下角为原点，适当建立坐标系）。",
    "optionalTitle": "挑战题：象限符号探索",
    "optionalDesc": "在平面直角坐标系中，点P(a,b)满足ab>0，且a+b<0，则点P在第几象限？说明理由。",
    "designIntent": "分层设计：基础题巩固核心技能，应用题联系生活，挑战题发展推理能力。",
    "differentiationNote": "基础薄弱学生只做必做题；学有余力学生挑战选做题；应用练习可小组交流。"
  },
  "boardDesign": {
    "layout": "左半部分：平面直角坐标系示意图（标明x轴、y轴、原点、象限及符号特征）；右半部分：有序数对定义 → 坐标表示（a,b）→ 描点方法。",
    "keyElements": [
      "有序数对",
      "x轴（横轴）",
      "y轴（纵轴）",
      "原点",
      "象限",
      "坐标（a,b）"
    ],
    "structureLogic": "从左到右：从概念到应用；从上到下：从抽象到具体。"
  },
  "reflection": {
    "targetAchievement": "预计多数学生能掌握坐标表示与描点，但象限符号特征可能部分学生需课后巩固。",
    "improvementMeasures": [
      "增加象限符号的顺口溜帮助记忆",
      "在练习中增加判断象限的题型"
    ],
    "notableObservations": "关注学生在尝试阶段是否主动思考，避免直接告知答案。"
  },
  "difficultyDesign": {
    "targetDifficulty": "核心困难：如何用一对有序数（坐标）表示平面上点的位置，特别是坐标的顺序和符号意义。",
    "educationalValue": "这个困难促使学生从一维数轴思维向二维坐标思维跨越，是数形结合思想的起点，具有重要认知价值。",
    "zpdAlignment": "学生已有数轴和有序数对基础，在教师引导下通过类比和尝试，可以跨越最近发展区。",
    "meaninglessObstacles": [
      "复杂的坐标系背景（如非整数坐标）",
      "过多象限符号记忆口诀"
    ],
    "motivationStrategy": "自主性：让学生用自己的方式尝试表示点；胜任感：通过成功描点获得成就感；关系感：小组交流分享。",
    "difficultyFirst": "在讲解坐标系前，先让学生尝试在网格纸上表示点的位置，制造认知冲突。",
    "processPreservation": "学生保留尝试的草稿纸，用于对比正确方法，反思错误。",
    "abstractionProtection": "先通过具体情境（电影院座位）建立感性认识，再抽象到坐标系概念，避免过早进入纯粹符号运算。"
  }
}